testcontainers/nginx/__init__.py
tests/test_nginx.py
testcontainers_nginx-0.0.1rc1.dist-info/METADATA
testcontainers_nginx-0.0.1rc1.dist-info/WHEEL
testcontainers_nginx-0.0.1rc1.dist-info/top_level.txt
testcontainers_nginx-0.0.1rc1.dist-info/RECORD
